{
  "value": [
    {
      "id": 272058664,
      "interfaceName": "cable-mac 1.0",
      "ip4Addresses": [
        {
          "prefixLength": 24,
          "addressUsage": "PRIMARY",
          "ip": "10.254.216.1"
        }
      ],
      "ip6Addresses": [],
      "vrfInstance": "default",
      "virtualDevice": "",
      "description": "",
      "enabled": true,
      "level3": true,
      "macAddress": "0000.0000.0000"
    },
    {
      "id": 272058665,
      "interfaceName": "link-aggregate 1.0",
      "ip4Addresses": [
        {
          "prefixLength": 30,
          "addressUsage": "PRIMARY",
          "ip": "213.51.225.170"
        }
      ],
      "ip6Addresses": [],
      "vrfInstance": "default",
      "virtualDevice": "",
      "description": "",
      "enabled": true,
      "level3": true,
      "macAddress": "0000.0000.0000"
    },
    {
      "id": 272058666,
      "interfaceName": "link-aggregate 1.201",
      "ip4Addresses": [
        {
          "prefixLength": 30,
          "addressUsage": "PRIMARY",
          "ip": "213.51.197.170"
        }
      ],
      "ip6Addresses": [],
      "vrfInstance": "default",
      "virtualDevice": "",
      "description": "",
      "enabled": true,
      "level3": true,
      "macAddress": "0000.0000.0000"
    },
    {
      "id": 272058667,
      "interfaceName": "link-aggregate 2.0",
      "ip4Addresses": [
        {
          "prefixLength": 30,
          "addressUsage": "PRIMARY",
          "ip": "213.51.225.174"
        }
      ],
      "ip6Addresses": [],
      "vrfInstance": "default",
      "virtualDevice": "",
      "description": "",
      "enabled": true,
      "level3": true,
      "macAddress": "0000.0000.0000"
    },
    {
      "id": 272058668,
      "interfaceName": "link-aggregate 2.251",
      "ip4Addresses": [
        {
          "prefixLength": 30,
          "addressUsage": "PRIMARY",
          "ip": "213.51.197.174"
        }
      ],
      "ip6Addresses": [],
      "vrfInstance": "default",
      "virtualDevice": "",
      "description": "",
      "enabled": true,
      "level3": true,
      "macAddress": "0000.0000.0000"
    },
    {
      "id": 272058669,
      "interfaceName": "loopback 0",
      "ip4Addresses": [
        {
          "prefixLength": 32,
          "addressUsage": "PRIMARY",
          "ip": "213.51.253.18"
        }
      ],
      "ip6Addresses": [],
      "vrfInstance": "default",
      "virtualDevice": "",
      "description": "",
      "enabled": true,
      "level3": true,
      "macAddress": "0000.0000.0000"
    },
    {
      "id": 272058670,
      "interfaceName": "ethernet 6/0.0",
      "ip4Addresses": [
        {
          "prefixLength": 24,
          "addressUsage": "PRIMARY",
          "ip": "172.30.215.16"
        }
      ],
      "ip6Addresses": [],
      "vrfInstance": "default",
      "virtualDevice": "",
      "description": "",
      "enabled": true,
      "level3": true,
      "macAddress": "0000.0000.0000"
    }
  ],
  "cached_at": "2026-01-04T01:25:39.522236",
  "key": "device_interfaces_10978"
}